{
	"format_version": "1.20.80",
	"minecraft:entity": {
		"description": {
			"identifier": "fv:command_flag_summon",
			"is_summonable": true,
			"is_spawnable": false
		},
		"component_groups": {
			"despawn": {
				"minecraft:instant_despawn": {
					"remove_child_entities": true
				},
				"minecraft:spawn_entity": {
					"entities": {
						"min_wait_time": 0,
						"max_wait_time": 0,
						"num_to_spawn": 1,
						"single_use": true,
						"spawn_item": "fv:command_flag"
					}
				}
			}
		},
		"components": {
			"minecraft:collision_box": {
				"height": 1.9,
				"width": 0
			},
			"minecraft:type_family": {
				"family": [
					"irongolem"
				]
			},
			"minecraft:health": {
				"value": 1,
				"max": 1
			},
			"minecraft:physics": {},
			"minecraft:pushable": {
				"is_pushable": false,
				"is_pushable_by_piston": false
			},
			"minecraft:damage_sensor": {
				"triggers": [
					{
						"on_damage": {
							"filters": {
								"test": "is_family",
								"subject": "other",
								"operator": "!=",
								"value": "irongolem"
							},
							"event": "despawn",
							"target": "self"
						},
						"deals_damage": false
					},
					{
						"on_damage": {
							"filters": {
								"test": "is_family",
								"subject": "other",
								"value": "irongolem"
							}
						},
						"deals_damage": false
					}
				]
			}
		},
		"events": {
			"minecraft:entity_spawned": {
				"queue_command": {
					"command": "function command_flag_summon"
				}
			},
			"despawn": {
				"add": {
					"component_groups": [
						"despawn"
					]
				}
			}
		}
	}
}