{
	"format_version": "1.16.0",
	"minecraft:geometry": [
		{
			"description": {
				"identifier": "geometry.64_item_size",
				"texture_width": 64,
				"texture_height": 64,
				"visible_bounds_width": 1,
				"visible_bounds_height": 1,
				"visible_bounds_offset": [
					0,
					0,
					0
				]
			},
			"bones": [
				{
					"name": "rightItem",
					"pivot": [
						0,
						0,
						0
					],
					"binding": "q.item_slot_to_bone_name(c.item_slot)"
				},
				{
					"name": "spear",
					"parent": "rightItem",
					"pivot": [
						0,
						0,
						0
					],
					"texture_meshes": [
						{
							"texture": "default",
							"position": [
								0,
								44,
								-10.5
							],
							"rotation": [
								0,
								45,
								-90
							]
						}
					]
				}
			]
		}
	]
}